ndd_rest_tools/__init__.py
ndd_rest_tools/main.py
ndd_rest_tools/models.py
ndd_rest_tools/proxy.py
ndd_rest_tools/utils.py
ndd_rest_tools/welcome.py
ndd_rest_tools-1.0.6.dist-info/METADATA
ndd_rest_tools-1.0.6.dist-info/WHEEL
ndd_rest_tools-1.0.6.dist-info/entry_points.txt
ndd_rest_tools-1.0.6.dist-info/top_level.txt
ndd_rest_tools-1.0.6.dist-info/RECORD
